{"errors":[],"warnings":[],"namedChunkGroups":{"app":{"chunks":[3,0],"assets":["webpack-runtime-94caf9254e26103fbd79.js","webpack-runtime-94caf9254e26103fbd79.js.map","app-184d10578604e66301c7.js","app-184d10578604e66301c7.js.map"],"children":{},"childAssets":{}},"component---src-pages-index-js":{"chunks":[2,4,1],"assets":["styles.d0163e054c20d52695ca.css","styles-538af7cd65b211ad8ab1.js","styles-538af7cd65b211ad8ab1.js.map","4-656cfb93e6ccdb3f0dd7.js","4-656cfb93e6ccdb3f0dd7.js.map","component---src-pages-index-js-721516c1ba461c1d6cee.js","component---src-pages-index-js-721516c1ba461c1d6cee.js.map"],"children":{},"childAssets":{}}},"assetsByChunkName":{"app":["webpack-runtime-94caf9254e26103fbd79.js","app-184d10578604e66301c7.js"],"component---src-pages-index-js":["styles.d0163e054c20d52695ca.css","styles-538af7cd65b211ad8ab1.js","4-656cfb93e6ccdb3f0dd7.js","component---src-pages-index-js-721516c1ba461c1d6cee.js"]}}